bhokacha/__init__.py
bhokacha/pal.py
bhokacha-0.2.0.dist-info/METADATA
bhokacha-0.2.0.dist-info/WHEEL
bhokacha-0.2.0.dist-info/top_level.txt
bhokacha-0.2.0.dist-info/RECORD
