Metadata-Version: 2.1
Name: bhokacha
Version: 0.2.0
Summary: My next Python library
Author: Me
License: MIT
